<?xml version="1.0" encoding="utf-8" ?><dwsync><file name="burningman1.jpeg" server="academy-webdesign1.com//public_html/travel_site/" local="3730394693" remote="3732228300" Dst="-1" /><file name="cityscape2.jpeg" server="academy-webdesign1.com//public_html/travel_site/" local="3730315335" remote="3732228300" Dst="-1" /><file name="zengrid.png" server="academy-webdesign1.com//public_html/travel_site/" local="3728440708" remote="3732228300" Dst="-1" /><file name="machupicchu.jpeg" server="academy-webdesign1.com//public_html/travel_site/" local="3730377868" remote="3732228300" Dst="-1" /><file name="cityscape1.jpeg" server="academy-webdesign1.com//public_html/travel_site/" local="3730313032" remote="3732228300" Dst="-1" /><file name="travelboat_med.jpg" server="academy-webdesign1.com//public_html/travel_site/" local="3730299823" remote="3732228300" Dst="-1" /><file name="travelboat_sm.jpg" server="academy-webdesign1.com//public_html/travel_site/" local="3730299946" remote="3732228300" Dst="-1" /><file name="diwali.jpeg" server="academy-webdesign1.com//public_html/travel_site/" local="3730397936" remote="3732228300" Dst="-1" /><file name="travelboat_xsm.jpg" server="academy-webdesign1.com//public_html/travel_site/" local="3730299738" remote="3732228300" Dst="-1" /><file name="travelboat.JPG" server="academy-webdesign1.com//public_html/travel_site/" local="3718764279" remote="3732228300" Dst="-1" /><file name="bangkok.jpeg" server="academy-webdesign1.com//public_html/travel_site/" local="3730376739" remote="3732228300" Dst="-1" /><file name="cinqueterre.jpg" server="academy-webdesign1.com//public_html/travel_site/" local="3730375569" remote="3732228300" Dst="-1" /><file name="burningman2.jpeg" server="academy-webdesign1.com//public_html/travel_site/" local="3730394754" remote="3732228300" Dst="-1" /><file name="card-img.png" server="academy-webdesign1.com//public_html/travel_site/" local="3722453411" remote="3732228300" Dst="-1" /><file name="mask.png" server="academy-webdesign1.com//public_html/travel_site/" local="3730338803" remote="3732228300" Dst="-1" /><file name="lagos.jpeg" server="academy-webdesign1.com//public_html/travel_site/" local="3730386436" remote="3732228300" Dst="-1" /><file name="diamuertos.jpeg" server="academy-webdesign1.com//public_html/travel_site/" local="3730398250" remote="3732228300" Dst="-1" /><file name="yosemite1.jpeg" server="academy-webdesign1.com//public_html/travel_site/" local="3730597276" remote="3732228300" Dst="-1" /><file name="yosemite2.jpeg" server="academy-webdesign1.com//public_html/travel_site/" local="3730597621" remote="3732228300" Dst="-1" /><file name="Virginia-Paradise2.jpg" server="academy-webdesign1.com//public_html/travel_site/" local="3730596066" remote="3732228300" Dst="-1" /><file name="Virginia-Paradise1.png" server="academy-webdesign1.com//public_html/travel_site/" local="3730596013" remote="3732228300" Dst="-1" /><file name="canyon1.jpeg" server="academy-webdesign1.com//public_html/travel_site/" local="3730859888" remote="3732228300" Dst="-1" /><file name="palm1.jpeg" server="academy-webdesign1.com//public_html/travel_site/" local="3730858080" remote="3732228300" Dst="-1" /><file name="muertos2.jpeg" server="academy-webdesign1.com//public_html/travel_site/" local="3732744551" remote="3732754800" Dst="-1" /><file name="tesla.jpeg" server="academy-webdesign1.com//public_html/travel_site/" local="3732738187" remote="3732754800" Dst="-1" /><file name="hondafit.jpeg" server="academy-webdesign1.com//public_html/travel_site/" local="3732738365" remote="3732754800" Dst="-1" /><file name="diwali2.jpeg" server="academy-webdesign1.com//public_html/travel_site/" local="3732745620" remote="3732754800" Dst="-1" /><file name="hotelgratis.jpeg" server="academy-webdesign1.com//public_html/travel_site/" local="3732662888" remote="3732754800" Dst="-1" /><file name="cottage.jpeg" server="academy-webdesign1.com//public_html/travel_site/" local="3732671725" remote="3732754800" Dst="-1" /><file name="resorthotel.jpeg" server="academy-webdesign1.com//public_html/travel_site/" local="3732663044" remote="3732754800" Dst="-1" /><file name="bungalow.jpeg" server="academy-webdesign1.com//public_html/travel_site/" local="3732664048" remote="3732754800" Dst="-1" /><file name="palacehotel.jpeg" server="academy-webdesign1.com//public_html/travel_site/" local="3732663218" remote="3732754800" Dst="-1" /><file name="ferrari.jpeg" server="academy-webdesign1.com//public_html/travel_site/" local="3732738040" remote="3732754800" Dst="-1" /><file name="hangglidenz.jpeg" server="academy-webdesign1.com//public_html/travel_site/" local="3732847195" remote="3732925320" Dst="-1" /><file name="hypersonic.jpeg" server="academy-webdesign1.com//public_html/travel_site/" local="3732842264" remote="3732925320" Dst="-1" /><file name="bikingvancouver.jpeg" server="academy-webdesign1.com//public_html/travel_site/" local="3732902906" remote="3732925320" Dst="-1" /><file name="aurora-borealis.jpg" server="academy-webdesign1.com//public_html/travel_site/" local="3732816917" remote="3732925320" Dst="-1" /><file name="peruvian.jpeg" server="academy-webdesign1.com//public_html/travel_site/" local="3732839958" remote="3732925320" Dst="-1" /><file name="La-Jolla-downtown.jpeg" server="academy-webdesign1.com//public_html/travel_site/" local="3732846438" remote="3732925320" Dst="-1" /><file name="hammock.jpeg" server="academy-webdesign1.com//public_html/travel_site/" local="3732889452" remote="3732925320" Dst="-1" /><file name="copperfield.jpeg" server="academy-webdesign1.com//public_html/travel_site/" local="3732819612" remote="3732925320" Dst="-1" /><file name="covidspikes.jpeg" server="academy-webdesign1.com//public_html/travel_site/" local="3732885824" remote="3732925320" Dst="-1" /><file name="teslahovercar.jpeg" server="academy-webdesign1.com//public_html/travel_site/" local="3732841788" remote="3732925320" Dst="-1" /><file name="herb.png" server="academy-webdesign1.com//public_html/travel_site/" local="3732903478" remote="3732925320" Dst="-1" /><file name="ceo.jpeg" server="academy-webdesign1.com//public_html/travel_site/" local="3732824762" remote="3732925320" Dst="-1" /><file name="avatar.jpeg" server="academy-webdesign1.com//public_html/travel_site/" local="3732840934" remote="3732925320" Dst="-1" /><file name="teleporter.jpeg" server="academy-webdesign1.com//public_html/travel_site/" local="3732823091" remote="3732925320" Dst="-1" /><file name="yellowstone.jpeg" server="academy-webdesign1.com//public_html/travel_site/" local="3732978838" remote="3733001940" Dst="-1" /><file name="canneryrow.jpeg" server="academy-webdesign1.com//public_html/travel_site/" local="3732976084" remote="3733001940" Dst="-1" /><file name="disneydowntown.jpeg" server="academy-webdesign1.com//public_html/travel_site/" local="3732976135" remote="3733001940" Dst="-1" /><file name="jungle.jpeg" server="academy-webdesign1.com//public_html/travel_site/" local="3732978001" remote="3733001940" Dst="-1" /><file name="disneyfountain.jpeg" server="academy-webdesign1.com//public_html/travel_site/" local="3732976060" remote="3733001940" Dst="-1" /><file name="mickey.jpeg" server="academy-webdesign1.com//public_html/travel_site/" local="3732976355" remote="3733001940" Dst="-1" /><file name="disneymountain.jpeg" server="academy-webdesign1.com//public_html/travel_site/" local="3732976010" remote="3733001940" Dst="-1" /><file name="universal.jpeg" server="academy-webdesign1.com//public_html/travel_site/" local="3732978553" remote="3733001940" Dst="-1" /><file name="paradise.jpeg" server="academy-webdesign1.com//public_html/travel_site/" local="3732975626" remote="3733001940" Dst="-1" /><file name="disneycastle.jpeg" server="academy-webdesign1.com//public_html/travel_site/" local="3732975910" remote="3733001940" Dst="-1" /><file name="haunted.jpeg" server="academy-webdesign1.com//public_html/travel_site/" local="3732977746" remote="3733001940" Dst="-1" /><file name="seychelles.jpeg" server="academy-webdesign1.com//public_html/travel_site/" local="3733058979" remote="3733078020" Dst="-1" /><file name="romansquare.jpeg" server="academy-webdesign1.com//public_html/travel_site/" local="3733066063" remote="3733078020" Dst="-1" /><file name="castel.jpeg" server="academy-webdesign1.com//public_html/travel_site/" local="3733065740" remote="3733078020" Dst="-1" /><file name="villaborghese.webp" server="academy-webdesign1.com//public_html/travel_site/" local="3733070041" remote="3733078020" Dst="-1" /><file name="trevifountain.jpeg" server="academy-webdesign1.com//public_html/travel_site/" local="3733065654" remote="3733078020" Dst="-1" /><file name="romanforum.jpeg" server="academy-webdesign1.com//public_html/travel_site/" local="3733065573" remote="3733078020" Dst="-1" /><file name="stpeters.jpeg" server="academy-webdesign1.com//public_html/travel_site/" local="3733065811" remote="3733078020" Dst="-1" /><file name="mostar.jpeg" server="academy-webdesign1.com//public_html/travel_site/" local="3733058571" remote="3733078020" Dst="-1" /><file name="vaticansistinechapel.jpeg" server="academy-webdesign1.com//public_html/travel_site/" local="3733065990" remote="3733078020" Dst="-1" /><file name="tivoli.jpeg" server="academy-webdesign1.com//public_html/travel_site/" local="3733069833" remote="3733078020" Dst="-1" /><file name="colosseum.jpeg" server="academy-webdesign1.com//public_html/travel_site/" local="3733065606" remote="3733078020" Dst="-1" /><file name="paris.jpeg" server="academy-webdesign1.com//public_html/travel_site/" local="3733059562" remote="3733078020" Dst="-1" /><file name="templeagrippa.jpeg" server="academy-webdesign1.com//public_html/travel_site/" local="3733066779" remote="3733078020" Dst="-1" /><file name="romeitaly.jpeg" server="academy-webdesign1.com//public_html/travel_site/" local="3733066032" remote="3733078020" Dst="-1" /><file name="tahoe3.jpeg" server="academy-webdesign1.com//public_html/travel_site/" local="3733153740" remote="3733162560" Dst="-1" /><file name="tahoe5.jpeg" server="academy-webdesign1.com//public_html/travel_site/" local="3733154055" remote="3733162560" Dst="-1" /><file name="tahoe2.jpeg" server="academy-webdesign1.com//public_html/travel_site/" local="3733153974" remote="3733162560" Dst="-1" /><file name="maunakea.jpeg" server="academy-webdesign1.com//public_html/travel_site/" local="3733152449" remote="3733162560" Dst="-1" /><file name="tahoe6.jpeg" server="academy-webdesign1.com//public_html/travel_site/" local="3733154071" remote="3733162560" Dst="-1" /><file name="tahoe4.jpeg" server="academy-webdesign1.com//public_html/travel_site/" local="3733154039" remote="3733162560" Dst="-1" /><file name="napaballooning.jpeg" server="academy-webdesign1.com//public_html/travel_site/" local="3733153136" remote="3733162560" Dst="-1" /><file name="tahoe1.jpeg" server="academy-webdesign1.com//public_html/travel_site/" local="3733153836" remote="3733162560" Dst="-1" /><file name="cortina.jpeg" server="academy-webdesign1.com//public_html/travel_site/" local="3733151687" remote="3733162560" Dst="-1" /><file name="chinapeaks.jpeg" server="academy-webdesign1.com//public_html/travel_site/" local="3733236089" remote="3733253460" Dst="-1" /><file name="istanbul.jpeg" server="academy-webdesign1.com//public_html/travel_site/" local="3733231389" remote="3733253460" Dst="-1" /><file name="pietrelcina.webp" server="academy-webdesign1.com//public_html/travel_site/" local="3733235226" remote="3733253460" Dst="-1" /><file name="tao.jpeg" server="academy-webdesign1.com//public_html/travel_site/" local="3733236587" remote="3733253460" Dst="-1" /><file name="tajmajal.jpeg" server="academy-webdesign1.com//public_html/travel_site/" local="3733237305" remote="3733253460" Dst="-1" /><file name="indiamuseum.jpeg" server="academy-webdesign1.com//public_html/travel_site/" local="3733237500" remote="3733253460" Dst="-1" /><file name="misty.jpeg" server="academy-webdesign1.com//public_html/travel_site/" local="3733236679" remote="3733253460" Dst="-1" /><file name="gethsemane.jpeg" server="academy-webdesign1.com//public_html/travel_site/" local="3733230753" remote="3733253460" Dst="-1" /><file name="pietrelcina.jpeg" server="academy-webdesign1.com//public_html/travel_site/" local="3733235287" remote="3733253460" Dst="-1" /><file name="israel.jpeg" server="academy-webdesign1.com//public_html/travel_site/" local="3733231007" remote="3733253460" Dst="-1" /><file name="budha.jpeg" server="academy-webdesign1.com//public_html/travel_site/" local="3733237875" remote="3733253460" Dst="-1" /><file name="pio.jpeg" server="academy-webdesign1.com//public_html/travel_site/" local="3733235447" remote="3733253460" Dst="-1" /><file name="tajmajal.webp" server="academy-webdesign1.com//public_html/travel_site/" local="3733237696" remote="3733253460" Dst="-1" /><file name="egypt.jpeg" server="academy-webdesign1.com//public_html/travel_site/" local="3733231150" remote="3733253460" Dst="-1" /><file name="PietrelcinaView.jpeg" server="academy-webdesign1.com//public_html/travel_site/" local="3733235273" remote="3733253460" Dst="-1" /><file name="gusti.jpg" server="academy-webdesign1.com//public_html/travel_site/" local="3733356857" remote="3733376100" Dst="-1" /></dwsync>